Metadata-Version: 2.1
Name: tiered-antibiotic-resistance-model
Version: 2.0.3
Summary: A validated computational model of the spread of an antibiotic resistant pathogens in a hospital, with and without our diagnostic tool for quickly identifying it
Home-page: https://github.com/Warwick-iGEM-2021/modelling
Author: Edmund Goodman
Author-email: egoodman3141@gmail.com
License: MIT
Download-URL: https://github.com/Warwick-iGEM-2021/modelling/archive/refs/tags/v2.0.3.tar.gz
Keywords: iGEM,synthetic biology,model
Platform: UNKNOWN
Classifier: Development Status :: 5 - Production/Stable
Classifier: Intended Audience :: Science/Research
Classifier: Topic :: Scientific/Engineering :: Bio-Informatics
Classifier: License :: OSI Approved :: MIT License
Classifier: Programming Language :: Python :: 3
Classifier: Programming Language :: Python :: 3.4
Classifier: Programming Language :: Python :: 3.5
Classifier: Programming Language :: Python :: 3.6
